recce/VERSION
recce/__init__.py
recce/artifact.py
recce/cli.py
recce/config.py
recce/connect_to_cloud.py
recce/core.py
recce/diff.py
recce/exceptions.py
recce/git.py
recce/github.py
recce/mcp_server.py
recce/pull_request.py
recce/run.py
recce/server.py
recce/summary.py
recce/websocket.py
recce/adapter/__init__.py
recce/adapter/base.py
recce/adapter/sqlmesh_adapter.py
recce/adapter/dbt_adapter/__init__.py
recce/adapter/dbt_adapter/dbt_version.py
recce/apis/__init__.py
recce/apis/check_api.py
recce/apis/check_events_api.py
recce/apis/check_func.py
recce/apis/run_api.py
recce/apis/run_func.py
recce/data/.gitkeep
recce/data/404.html
recce/data/__next.@lineage.!KHNsb3Qp.__PAGE__.txt
recce/data/__next.@lineage.!KHNsb3Qp.txt
recce/data/__next.__PAGE__.txt
recce/data/__next._full.txt
recce/data/__next._head.txt
recce/data/__next._index.txt
recce/data/__next._tree.txt
recce/data/auth_callback.html
recce/data/favicon.ico
recce/data/index.html
recce/data/index.txt
recce/data/404/index.html
recce/data/_next/static/chunks/11a1a024a3eceed4.js
recce/data/_next/static/chunks/123e829f169c0100.js
recce/data/_next/static/chunks/1bbfc841a3bbdeab.js
recce/data/_next/static/chunks/1c9a95df941df4af.js
recce/data/_next/static/chunks/1e4334d18b8a3acd.css
recce/data/_next/static/chunks/2bc5c51da5e54973.js
recce/data/_next/static/chunks/2c616f5866bab3b0.js
recce/data/_next/static/chunks/43e0b34d1dad593f.css
recce/data/_next/static/chunks/49dd9a35f25a3c78.js
recce/data/_next/static/chunks/55f691775a443af1.js
recce/data/_next/static/chunks/5c80abea6520f14a.js
recce/data/_next/static/chunks/5d86ee6b69e79ebd.js
recce/data/_next/static/chunks/63c181fc1f111c6c.js
recce/data/_next/static/chunks/64421f4fc69a00fe.js
recce/data/_next/static/chunks/6fd03f4f192637cb.js
recce/data/_next/static/chunks/729126a59d33adfc.js
recce/data/_next/static/chunks/7bb921acbf2d3876.js
recce/data/_next/static/chunks/8a5bd6fe3abc8091.css
recce/data/_next/static/chunks/8de4120d236036e3.js
recce-1.34.1.dist-info/METADATA
recce-1.34.1.dist-info/WHEEL
recce-1.34.1.dist-info/entry_points.txt
recce-1.34.1.dist-info/licenses/LICENSE
recce-1.34.1.dist-info/RECORD
