Metadata-Version: 2.4
Name: recce
Version: 1.34.1
Summary: Environment diff tool for dbt
Project-URL: Bug Tracker, https://github.com/InfuseAI/recce/issues
Project-URL: Homepage, https://github.com/InfuseAI/recce
Author-email: InfuseAI Dev Team <dev@infuseai.io>
License: Apache-2.0
License-File: LICENSE
Classifier: Development Status :: 4 - Beta
Classifier: License :: OSI Approved :: Apache Software License
Classifier: Operating System :: OS Independent
Classifier: Programming Language :: Python :: 3.9
Classifier: Programming Language :: Python :: 3.10
Classifier: Programming Language :: Python :: 3.11
Classifier: Programming Language :: Python :: 3.12
Classifier: Programming Language :: Python :: 3.13
Requires-Python: >=3.9
Requires-Dist: boto3
Requires-Dist: click>=7.1
Requires-Dist: deepdiff<9.0,>=7.0
Requires-Dist: fastapi
Requires-Dist: gitpython
Requires-Dist: itsdangerous
Requires-Dist: jinja2
Requires-Dist: packaging
Requires-Dist: portalocker
Requires-Dist: py-markdown-table
Requires-Dist: pydantic
Requires-Dist: pygithub
Requires-Dist: python-dateutil
Requires-Dist: python-multipart
Requires-Dist: pytz
Requires-Dist: requests>=2.28.1
Requires-Dist: rich>=12.0.0
Requires-Dist: ruamel-yaml>=0.18.6
Requires-Dist: sentry-sdk
Requires-Dist: sqlglot<28.0,>=27.29.0
Requires-Dist: uvicorn
Requires-Dist: watchdog
Requires-Dist: websockets
Provides-Extra: dev
Requires-Dist: black>=25.1.0; extra == 'dev'
Requires-Dist: dbt-duckdb; extra == 'dev'
Requires-Dist: flake8>=7.2.0; extra == 'dev'
Requires-Dist: httpx; extra == 'dev'
Requires-Dist: isort>=6.0.1; extra == 'dev'
Requires-Dist: pandas; extra == 'dev'
Requires-Dist: pre-commit>=4.2.0; extra == 'dev'
Requires-Dist: pytest-asyncio<1.0,>=0.23; extra == 'dev'
Requires-Dist: pytest-cov; extra == 'dev'
Requires-Dist: pytest-flake8; extra == 'dev'
Requires-Dist: pytest-mypy; extra == 'dev'
Requires-Dist: pytest>=4.6; extra == 'dev'
Requires-Dist: tox; extra == 'dev'
Requires-Dist: tox-uv; extra == 'dev'
Requires-Dist: twine; extra == 'dev'
Provides-Extra: mcp
Requires-Dist: mcp>=1.0.0; (python_version >= '3.10') and extra == 'mcp'
